coinmarketcap_with_cache/__init__.py
coinmarketcap_with_cache/core.py
coinmarketcap_with_cache-5.1.0.dist-info/LICENSE
coinmarketcap_with_cache-5.1.0.dist-info/METADATA
coinmarketcap_with_cache-5.1.0.dist-info/WHEEL
coinmarketcap_with_cache-5.1.0.dist-info/top_level.txt
coinmarketcap_with_cache-5.1.0.dist-info/RECORD
